{"name":"Ccsds-standalone","body":"# Ccsds - Module used to decode or encode CCSDS TC/TM\r\n\r\n## SYNOPSIS\r\n\r\nThis library allows decoding and encoding of CCSDS stream defined in the PSS/ECSS standards.\r\nThe current module Ccsds.pm only exports $VERSION which can be retried to know the version of the library. \r\n\r\n    use Ccsds::Utils qw(tm_verify_crc);\r\n    use Ccsds::TM::Frame qw($TMFrame);\r\n    use Ccsds::TM::SourcePacket qw($TMSourcePacket $TMSourcePacketHeader $TMSourceSecondaryHeader) ;\r\n    use Data::Dumper;\r\n\r\n    #Decode binary input as CCSDS TM Source Packet\r\n    my $tm         = $TMSourcePacket->parse($input);\r\n\r\n    my $header     = $tm->{'Packet Header'};\r\n    my $dataf      = $tm->{'Packet Data Field'};\r\n    my $data       = $dataf->{'Data Field'};\r\n    my $pid        = $header->{'Packet Id'}->{'Apid'}->{'PID'};\r\n    my $sec_header = $data->{'TMSourceSecondaryHeader'};\r\n    my $pus_data   = $data->{'PusData'};\r\n    my $pus_t      = $sec_header->{'Service Type'};\r\n    my $pus_st     = $sec_header->{'Service Subtype'};\r\n\r\n    my $ref_length = \\$f_header->{'Packet Sequence Control'}->{'Packet Length'};\r\n\r\n    #Correct packet_length for some broken traffic\r\n    if ( $pid == 6 and $pus_t == 3 and $pus_st == 25 ) {\r\n        $$ref_length_packet_length += 2;\r\n    }\r\n\r\n    #Rebuild Telemetry\r\n    $data = $TMSourcePacket->build($decoded);\r\n    patch_crc(\\$data);\r\n    \r\n    ...\r\n\r\n##AUTHOR\r\n\r\nLaurent KISLAIRE, C<< <teebeenator at gmail.com> >>\r\n\r\n##BUGS\r\n\r\nPlease report any bugs or feature requests to C<teebeenator at gmail.com>\r\n\r\n##SUPPORT\r\n\r\nYou can find documentation for this module with the perldoc command.\r\n\r\n    perldoc Ccsds\r\n\r\n\r\n##LICENSE AND COPYRIGHT\r\n\r\nCopyright 2010-2012 Laurent KISLAIRE.\r\n\r\nThis program is free software; you can redistribute it and/or modify it\r\nunder the terms of either: the GNU General Public License as published\r\nby the Free Software Foundation; or the Artistic License.\r\n\r\nSee http://dev.perl.org/licenses/ for more information.","tagline":"CCSDS encoder/decoder","google":"","note":"Don't delete this file! It's used internally to help with page regeneration."}